kicad_python-0.5.0.dist-info/licenses/LICENSE
kipy/__init__.py
kipy/board.py
kipy/board_types.py
kipy/client.py
kipy/common_types.py
kipy/errors.py
kipy/geometry.py
kipy/kicad.py
kipy/kicad_api_version.py
kipy/project.py
kipy/project_types.py
kipy/py.typed
kipy/wrapper.py
kipy/proto/__init__.py
kipy/proto/board/__init__.py
kipy/proto/board/board_commands_pb2.py
kipy/proto/board/board_commands_pb2.pyi
kipy/proto/board/board_pb2.py
kipy/proto/board/board_pb2.pyi
kipy/proto/board/board_types_pb2.py
kipy/proto/board/board_types_pb2.pyi
kipy/proto/common/__init__.py
kipy/proto/common/envelope_pb2.py
kipy/proto/common/envelope_pb2.pyi
kipy/proto/common/commands/__init__.py
kipy/proto/common/commands/base_commands_pb2.py
kipy/proto/common/commands/base_commands_pb2.pyi
kipy/proto/common/commands/editor_commands_pb2.py
kipy/proto/common/commands/editor_commands_pb2.pyi
kipy/proto/common/commands/project_commands_pb2.py
kipy/proto/common/commands/project_commands_pb2.pyi
kipy/proto/common/types/__init__.py
kipy/proto/common/types/base_types_pb2.py
kipy/proto/common/types/base_types_pb2.pyi
kipy/proto/common/types/enums_pb2.py
kipy/proto/common/types/enums_pb2.pyi
kipy/proto/common/types/project_settings_pb2.py
kipy/proto/common/types/project_settings_pb2.pyi
kipy/proto/schematic/schematic_commands_pb2.py
kipy/proto/schematic/schematic_commands_pb2.pyi
kipy/proto/schematic/schematic_types_pb2.py
kipy/proto/schematic/schematic_types_pb2.pyi
kipy/util/__init__.py
kipy/util/board_layer.py
kipy/util/proto.py
kipy/util/units.py
kicad_python-0.5.0.dist-info/METADATA
kicad_python-0.5.0.dist-info/WHEEL
kicad_python-0.5.0.dist-info/top_level.txt
kicad_python-0.5.0.dist-info/RECORD
