Metadata-Version: 2.4
Name: kicad-python
Version: 0.5.0
Summary: KiCad API Python Bindings
License-Expression: MIT
License-File: LICENSE
Author: The KiCad Development Team
Requires-Python: >=3.9
Classifier: Development Status :: 4 - Beta
Classifier: Intended Audience :: Developers
Classifier: Topic :: Scientific/Engineering :: Electronic Design Automation (EDA)
Classifier: Typing :: Typed
Requires-Dist: protobuf (>=5.29,<6)
Requires-Dist: pynng (>=0.8.0,<0.9.0)
Requires-Dist: typing_extensions (>=4.13.2) ; python_version < "3.13"
Project-URL: Documentation, https://docs.kicad.org/kicad-python-main/
Project-URL: Homepage, https://kicad.org/
Project-URL: Repository, https://gitlab.com/kicad/code/kicad-python
Project-URL: issues, https://gitlab.com/kicad/code/kicad-python/-/issues
